redshift_upload/__init__.py
redshift_upload/queries.py
redshift_upload/upload.py
redshift_upload-1.0.1.dist-info/LICENSE.txt
redshift_upload-1.0.1.dist-info/METADATA
redshift_upload-1.0.1.dist-info/WHEEL
redshift_upload-1.0.1.dist-info/top_level.txt
redshift_upload-1.0.1.dist-info/RECORD
